cjm_yolox_pytorch/__init__.py
cjm_yolox_pytorch/_modidx.py
cjm_yolox_pytorch/inference.py
cjm_yolox_pytorch/loss.py
cjm_yolox_pytorch/model.py
cjm_yolox_pytorch/simota.py
cjm_yolox_pytorch/utils.py
cjm_yolox_pytorch-0.2.0.dist-info/LICENSE
cjm_yolox_pytorch-0.2.0.dist-info/METADATA
cjm_yolox_pytorch-0.2.0.dist-info/WHEEL
cjm_yolox_pytorch-0.2.0.dist-info/entry_points.txt
cjm_yolox_pytorch-0.2.0.dist-info/top_level.txt
cjm_yolox_pytorch-0.2.0.dist-info/RECORD
