Metadata-Version: 2.1
Name: cjm-yolox-pytorch
Version: 0.2.0
Summary: A PyTorch implementation of the YOLOX object detection model based on the mmdetection implementation.
Home-page: https://github.com/cj-mills/cjm-yolox-pytorch
Author: cj-mills
Author-email: millscj.mills2@gmail.com
License: Apache Software License 2.0
Keywords: nbdev jupyter notebook python torch
Classifier: Development Status :: 4 - Beta
Classifier: Intended Audience :: Developers
Classifier: Natural Language :: English
Classifier: Programming Language :: Python :: 3.9
Classifier: Programming Language :: Python :: 3.10
Classifier: License :: OSI Approved :: Apache Software License
Requires-Python: >=3.9
License-File: LICENSE
Requires-Dist: torch
Requires-Dist: numpy
Requires-Dist: torchvision
Requires-Dist: cjm-psl-utils
Provides-Extra: dev
